elevator.v
module Elevator (
	input clk,
	input [4:0] in_btn, out_btn, in_snsr, out_snsr,
	input reset,
	output reg direction, motor
);

	reg [2:0] boundary_floor;
	reg [4:0] floor_requests;

	integer floor_timer;

	integer i;
	reg above, below;

	always @ (posedge clk, posedge reset) begin
		if (reset) begin
			boundary_floor = 0;
			floor_requests = 0;
			floor_timer = 0;
			above = 0;
			below = 0;

			direction = 0;
			motor = 0;
		end
		else begin
			for (i = 0; i < 5; i = i + 1) begin
				if (in_btn[i] || out_btn[i]) begin
					floor_requests[i] = 1;
				end
			end

			above = 0;
			below = 0;

			for (i = 0; i < 5; i = i + 1) begin
				if (floor_requests[i]) begin
					if (i > boundary_floor) above = 1;
					if (i < boundary_floor) below = 1;
				end
			end

			if (floor_timer > 0)
				floor_timer = floor_timer - 1;
			else if (in_snsr != 0 && out_snsr != 0) begin
				boundary_floor = ((in_snsr[0] == 1) ? 0 : (in_snsr[1] == 1) ? 1 : (in_snsr[2] == 1) ? 2 : (in_snsr[3] == 1) ? 3 : 4);
				if (above != below)
					direction = (above == 1) ? 1 : 0;
				if (floor_requests[boundary_floor] == 1) begin
					motor = 0;
					floor_timer = 100;
					floor_requests[boundary_floor] = 0;
				end
				else if ((boundary_floor == 0 && direction == 0) || (boundary_floor == 4 && direction == 1)) begin
					motor = 0;
				end
				else
					motor = 1;
			end
		end
	end
endmodule

tb.v
module TB;

	reg clk, reset;
	reg [4:0] in_btn, out_btn, in_snsr, out_snsr;

	wire direction, motor;

	Elevator elevator (
		.clk(clk),
		.in_btn(in_btn),
		.out_btn(out_btn),
		.in_snsr(in_snsr),
		.out_snsr(out_snsr),
		.reset(reset),
		.direction(direction),
		.motor(motor)
	);

	initial begin
		clk = 0;
	end

	always #5 clk = ~clk;

	initial begin

		// Level 0: reset

		in_btn = 0;
		out_btn = 0;
		in_snsr = 0;
		out_snsr = 0;
		reset = 1;
		#100;
		reset = 0;
		#100;
		in_snsr[0] = 1;
		out_snsr[0] = 1;
		#100;

		// Level 1: out button 3 pressed
		out_btn[3] = 1; #30; out_btn[3] = 0; #20;
		in_snsr[0] = 0; #50; out_snsr[0] = 0;
		#100;

		// Level 2: pass one floor
		in_snsr[1] = 1; #50; out_snsr[1] = 1;
		#50;
		in_snsr[1] = 0; #50; out_snsr[1] = 0;
		#50;

		// Level 3: out button 4 pressed
		out_btn[4] = 1; #30; out_btn[4] = 0; #20;
		in_snsr[2] = 1; #50; out_snsr[2] = 1;
		#50;
		in_snsr[2] = 0; #50; out_snsr[2] = 0;
		#100;

		// Level 4: reach floor 3
		in_snsr[3] = 1; #50; out_snsr[3] = 1;
		#1000;
		#50;
		in_snsr[3] = 0; #50; out_snsr[3] = 0;
		#50;

		// Level 5: in button 0 (lobby) pressed
		in_btn[0] = 1; #30; in_btn[0] = 0;

		// Level 6: reach floor 4
		#20; in_snsr[4] = 1; #50; out_snsr[4] = 1;
		#1000;
		#50;

		// Level 7: Go down
		in_snsr[4] = 0; #50; out_snsr[4] = 0;
		#100;
		in_snsr[3] = 1; #50; out_snsr[3] = 1;
		#50;
		in_snsr[3] = 0; #50; out_snsr[3] = 0;
		#50;
		
		// Level 8: in button 1 pressed
		in_btn[1] = 1; #30; in_btn[1] = 0; #20;
		in_snsr[2] = 1; #50; out_snsr[2] = 1;
		#50;
		in_snsr[2] = 0; #50; out_snsr[2] = 0;
		#100;

		// Level 9: reach floor 1
		in_snsr[1] = 1; #50; out_snsr[1] = 1;
		#1000;
		#50;
		in_snsr[1] = 0; #50; out_snsr[1] = 0;
		#100;

		// Level 10: reach lobby
		in_snsr[0] = 1; #50; out_snsr[0] = 1;
		#50;

		#100; $finish;
	end

	initial begin
		$dumpfile("result.vcd");
		$dumpvars(0, TB);
	end

endmodule

result.vcd
$date
	Wed Jun 26 20:34:06 2024
$end
$version
	Icarus Verilog
$end
$timescale
	1s
$end
$scope module TB $end
$var wire 1 ! motor $end
$var wire 1 " direction $end
$var reg 1 # clk $end
$var reg 5 $ in_btn [4:0] $end
$var reg 5 % in_snsr [4:0] $end
$var reg 5 & out_btn [4:0] $end
$var reg 5 ' out_snsr [4:0] $end
$var reg 1 ( reset $end
$scope module elevator $end
$var wire 1 # clk $end
$var wire 5 ) in_btn [4:0] $end
$var wire 5 * in_snsr [4:0] $end
$var wire 5 + out_btn [4:0] $end
$var wire 5 , out_snsr [4:0] $end
$var wire 1 ( reset $end
$var reg 1 - above $end
$var reg 1 . below $end
$var reg 3 / boundary_floor [2:0] $end
$var reg 1 " direction $end
$var reg 5 0 floor_requests [4:0] $end
$var reg 1 ! motor $end
$var integer 32 1 floor_timer [31:0] $end
$var integer 32 2 i [31:0] $end
$upscope $end
$upscope $end
$enddefinitions $end
$comment Show the parameter values. $end
$dumpall
$end
#0
$dumpvars
bx 2
b0 1
b0 0
b0 /
0.
0-
b0 ,
b0 +
b0 *
b0 )
1(
b0 '
b0 &
b0 %
b0 $
0#
0"
0!
$end
#5
1#
#10
0#
#15
1#
#20
0#
#25
1#
#30
0#
#35
1#
#40
0#
#45
1#
#50
0#
#55
1#
#60
0#
#65
1#
#70
0#
#75
1#
#80
0#
#85
1#
#90
0#
#95
1#
#100
0#
0(
#105
b101 2
1#
#110
0#
#115
b101 2
1#
#120
0#
#125
b101 2
1#
#130
0#
#135
b101 2
1#
#140
0#
#145
b101 2
1#
#150
0#
#155
b101 2
1#
#160
0#
#165
b101 2
1#
#170
0#
#175
b101 2
1#
#180
0#
#185
b101 2
1#
#190
0#
#195
b101 2
1#
#200
0#
b1 '
b1 ,
b1 %
b1 *
#205
b101 2
1#
#210
0#
#215
b101 2
1#
#220
0#
#225
b101 2
1#
#230
0#
#235
b101 2
1#
#240
0#
#245
b101 2
1#
#250
0#
#255
b101 2
1#
#260
0#
#265
b101 2
1#
#270
0#
#275
b101 2
1#
#280
0#
#285
b101 2
1#
#290
0#
#295
b101 2
1#
#300
0#
b1000 &
b1000 +
#305
1!
1"
1-
b1000 0
b101 2
1#
#310
0#
#315
1-
b101 2
1#
#320
0#
#325
1-
b101 2
1#
#330
0#
b0 &
b0 +
#335
1-
b101 2
1#
#340
0#
#345
1-
b101 2
1#
#350
0#
b0 %
b0 *
#355
1-
b101 2
1#
#360
0#
#365
1-
b101 2
1#
#370
0#
#375
1-
b101 2
1#
#380
0#
#385
1-
b101 2
1#
#390
0#
#395
1-
b101 2
1#
#400
0#
b0 '
b0 ,
#405
1-
b101 2
1#
#410
0#
#415
1-
b101 2
1#
#420
0#
#425
1-
b101 2
1#
#430
0#
#435
1-
b101 2
1#
#440
0#
#445
1-
b101 2
1#
#450
0#
#455
1-
b101 2
1#
#460
0#
#465
1-
b101 2
1#
#470
0#
#475
1-
b101 2
1#
#480
0#
#485
1-
b101 2
1#
#490
0#
#495
1-
b101 2
1#
#500
0#
b10 %
b10 *
#505
1-
b101 2
1#
#510
0#
#515
1-
b101 2
1#
#520
0#
#525
1-
b101 2
1#
#530
0#
#535
1-
b101 2
1#
#540
0#
#545
1-
b101 2
1#
#550
0#
b10 '
b10 ,
#555
b1 /
1-
b101 2
1#
#560
0#
#565
1-
b101 2
1#
#570
0#
#575
1-
b101 2
1#
#580
0#
#585
1-
b101 2
1#
#590
0#
#595
1-
b101 2
1#
#600
0#
b0 %
b0 *
#605
1-
b101 2
1#
#610
0#
#615
1-
b101 2
1#
#620
0#
#625
1-
b101 2
1#
#630
0#
#635
1-
b101 2
1#
#640
0#
#645
1-
b101 2
1#
#650
0#
b0 '
b0 ,
#655
1-
b101 2
1#
#660
0#
#665
1-
b101 2
1#
#670
0#
#675
1-
b101 2
1#
#680
0#
#685
1-
b101 2
1#
#690
0#
#695
1-
b101 2
1#
#700
0#
b10000 &
b10000 +
#705
1-
b11000 0
b101 2
1#
#710
0#
#715
1-
b101 2
1#
#720
0#
#725
1-
b101 2
1#
#730
0#
b0 &
b0 +
#735
1-
b101 2
1#
#740
0#
#745
1-
b101 2
1#
#750
0#
b100 %
b100 *
#755
1-
b101 2
1#
#760
0#
#765
1-
b101 2
1#
#770
0#
#775
1-
b101 2
1#
#780
0#
#785
1-
b101 2
1#
#790
0#
#795
1-
b101 2
1#
#800
0#
b100 '
b100 ,
#805
b10 /
1-
b101 2
1#
#810
0#
#815
1-
b101 2
1#
#820
0#
#825
1-
b101 2
1#
#830
0#
#835
1-
b101 2
1#
#840
0#
#845
1-
b101 2
1#
#850
0#
b0 %
b0 *
#855
1-
b101 2
1#
#860
0#
#865
1-
b101 2
1#
#870
0#
#875
1-
b101 2
1#
#880
0#
#885
1-
b101 2
1#
#890
0#
#895
1-
b101 2
1#
#900
0#
b0 '
b0 ,
#905
1-
b101 2
1#
#910
0#
#915
1-
b101 2
1#
#920
0#
#925
1-
b101 2
1#
#930
0#
#935
1-
b101 2
1#
#940
0#
#945
1-
b101 2
1#
#950
0#
#955
1-
b101 2
1#
#960
0#
#965
1-
b101 2
1#
#970
0#
#975
1-
b101 2
1#
#980
0#
#985
1-
b101 2
1#
#990
0#
#995
1-
b101 2
1#
#1000
0#
b1000 %
b1000 *
#1005
1-
b101 2
1#
#1010
0#
#1015
1-
b101 2
1#
#1020
0#
#1025
1-
b101 2
1#
#1030
0#
#1035
1-
b101 2
1#
#1040
0#
#1045
1-
b101 2
1#
#1050
0#
b1000 '
b1000 ,
#1055
b10000 0
b1100100 1
0!
b11 /
1-
b101 2
1#
#1060
0#
#1065
b1100011 1
1-
b101 2
1#
#1070
0#
#1075
b1100010 1
1-
b101 2
1#
#1080
0#
#1085
b1100001 1
1-
b101 2
1#
#1090
0#
#1095
b1100000 1
1-
b101 2
1#
#1100
0#
#1105
b1011111 1
1-
b101 2
1#
#1110
0#
#1115
b1011110 1
1-
b101 2
1#
#1120
0#
#1125
b1011101 1
1-
b101 2
1#
#1130
0#
#1135
b1011100 1
1-
b101 2
1#
#1140
0#
#1145
b1011011 1
1-
b101 2
1#
#1150
0#
#1155
b1011010 1
1-
b101 2
1#
#1160
0#
#1165
b1011001 1
1-
b101 2
1#
#1170
0#
#1175
b1011000 1
1-
b101 2
1#
#1180
0#
#1185
b1010111 1
1-
b101 2
1#
#1190
0#
#1195
b1010110 1
1-
b101 2
1#
#1200
0#
#1205
b1010101 1
1-
b101 2
1#
#1210
0#
#1215
b1010100 1
1-
b101 2
1#
#1220
0#
#1225
b1010011 1
1-
b101 2
1#
#1230
0#
#1235
b1010010 1
1-
b101 2
1#
#1240
0#
#1245
b1010001 1
1-
b101 2
1#
#1250
0#
#1255
b1010000 1
1-
b101 2
1#
#1260
0#
#1265
b1001111 1
1-
b101 2
1#
#1270
0#
#1275
b1001110 1
1-
b101 2
1#
#1280
0#
#1285
b1001101 1
1-
b101 2
1#
#1290
0#
#1295
b1001100 1
1-
b101 2
1#
#1300
0#
#1305
b1001011 1
1-
b101 2
1#
#1310
0#
#1315
b1001010 1
1-
b101 2
1#
#1320
0#
#1325
b1001001 1
1-
b101 2
1#
#1330
0#
#1335
b1001000 1
1-
b101 2
1#
#1340
0#
#1345
b1000111 1
1-
b101 2
1#
#1350
0#
#1355
b1000110 1
1-
b101 2
1#
#1360
0#
#1365
b1000101 1
1-
b101 2
1#
#1370
0#
#1375
b1000100 1
1-
b101 2
1#
#1380
0#
#1385
b1000011 1
1-
b101 2
1#
#1390
0#
#1395
b1000010 1
1-
b101 2
1#
#1400
0#
#1405
b1000001 1
1-
b101 2
1#
#1410
0#
#1415
b1000000 1
1-
b101 2
1#
#1420
0#
#1425
b111111 1
1-
b101 2
1#
#1430
0#
#1435
b111110 1
1-
b101 2
1#
#1440
0#
#1445
b111101 1
1-
b101 2
1#
#1450
0#
#1455
b111100 1
1-
b101 2
1#
#1460
0#
#1465
b111011 1
1-
b101 2
1#
#1470
0#
#1475
b111010 1
1-
b101 2
1#
#1480
0#
#1485
b111001 1
1-
b101 2
1#
#1490
0#
#1495
b111000 1
1-
b101 2
1#
#1500
0#
#1505
b110111 1
1-
b101 2
1#
#1510
0#
#1515
b110110 1
1-
b101 2
1#
#1520
0#
#1525
b110101 1
1-
b101 2
1#
#1530
0#
#1535
b110100 1
1-
b101 2
1#
#1540
0#
#1545
b110011 1
1-
b101 2
1#
#1550
0#
#1555
b110010 1
1-
b101 2
1#
#1560
0#
#1565
b110001 1
1-
b101 2
1#
#1570
0#
#1575
b110000 1
1-
b101 2
1#
#1580
0#
#1585
b101111 1
1-
b101 2
1#
#1590
0#
#1595
b101110 1
1-
b101 2
1#
#1600
0#
#1605
b101101 1
1-
b101 2
1#
#1610
0#
#1615
b101100 1
1-
b101 2
1#
#1620
0#
#1625
b101011 1
1-
b101 2
1#
#1630
0#
#1635
b101010 1
1-
b101 2
1#
#1640
0#
#1645
b101001 1
1-
b101 2
1#
#1650
0#
#1655
b101000 1
1-
b101 2
1#
#1660
0#
#1665
b100111 1
1-
b101 2
1#
#1670
0#
#1675
b100110 1
1-
b101 2
1#
#1680
0#
#1685
b100101 1
1-
b101 2
1#
#1690
0#
#1695
b100100 1
1-
b101 2
1#
#1700
0#
#1705
b100011 1
1-
b101 2
1#
#1710
0#
#1715
b100010 1
1-
b101 2
1#
#1720
0#
#1725
b100001 1
1-
b101 2
1#
#1730
0#
#1735
b100000 1
1-
b101 2
1#
#1740
0#
#1745
b11111 1
1-
b101 2
1#
#1750
0#
#1755
b11110 1
1-
b101 2
1#
#1760
0#
#1765
b11101 1
1-
b101 2
1#
#1770
0#
#1775
b11100 1
1-
b101 2
1#
#1780
0#
#1785
b11011 1
1-
b101 2
1#
#1790
0#
#1795
b11010 1
1-
b101 2
1#
#1800
0#
#1805
b11001 1
1-
b101 2
1#
#1810
0#
#1815
b11000 1
1-
b101 2
1#
#1820
0#
#1825
b10111 1
1-
b101 2
1#
#1830
0#
#1835
b10110 1
1-
b101 2
1#
#1840
0#
#1845
b10101 1
1-
b101 2
1#
#1850
0#
#1855
b10100 1
1-
b101 2
1#
#1860
0#
#1865
b10011 1
1-
b101 2
1#
#1870
0#
#1875
b10010 1
1-
b101 2
1#
#1880
0#
#1885
b10001 1
1-
b101 2
1#
#1890
0#
#1895
b10000 1
1-
b101 2
1#
#1900
0#
#1905
b1111 1
1-
b101 2
1#
#1910
0#
#1915
b1110 1
1-
b101 2
1#
#1920
0#
#1925
b1101 1
1-
b101 2
1#
#1930
0#
#1935
b1100 1
1-
b101 2
1#
#1940
0#
#1945
b1011 1
1-
b101 2
1#
#1950
0#
#1955
b1010 1
1-
b101 2
1#
#1960
0#
#1965
b1001 1
1-
b101 2
1#
#1970
0#
#1975
b1000 1
1-
b101 2
1#
#1980
0#
#1985
b111 1
1-
b101 2
1#
#1990
0#
#1995
b110 1
1-
b101 2
1#
#2000
0#
#2005
b101 1
1-
b101 2
1#
#2010
0#
#2015
b100 1
1-
b101 2
1#
#2020
0#
#2025
b11 1
1-
b101 2
1#
#2030
0#
#2035
b10 1
1-
b101 2
1#
#2040
0#
#2045
b1 1
1-
b101 2
1#
#2050
0#
#2055
b0 1
1-
b101 2
1#
#2060
0#
#2065
1!
1-
b101 2
1#
#2070
0#
#2075
1-
b101 2
1#
#2080
0#
#2085
1-
b101 2
1#
#2090
0#
#2095
1-
b101 2
1#
#2100
0#
b0 %
b0 *
#2105
1-
b101 2
1#
#2110
0#
#2115
1-
b101 2
1#
#2120
0#
#2125
1-
b101 2
1#
#2130
0#
#2135
1-
b101 2
1#
#2140
0#
#2145
1-
b101 2
1#
#2150
0#
b0 '
b0 ,
#2155
1-
b101 2
1#
#2160
0#
#2165
1-
b101 2
1#
#2170
0#
#2175
1-
b101 2
1#
#2180
0#
#2185
1-
b101 2
1#
#2190
0#
#2195
1-
b101 2
1#
#2200
0#
b1 $
b1 )
#2205
1.
1-
b10001 0
b101 2
1#
#2210
0#
#2215
1.
1-
b101 2
1#
#2220
0#
#2225
1.
1-
b101 2
1#
#2230
0#
b0 $
b0 )
#2235
1.
1-
b101 2
1#
#2240
0#
#2245
1.
1-
b101 2
1#
#2250
0#
b10000 %
b10000 *
#2255
1.
1-
b101 2
1#
#2260
0#
#2265
1.
1-
b101 2
1#
#2270
0#
#2275
1.
1-
b101 2
1#
#2280
0#
#2285
1.
1-
b101 2
1#
#2290
0#
#2295
1.
1-
b101 2
1#
#2300
0#
b10000 '
b10000 ,
#2305
b1 0
b1100100 1
0!
b100 /
1.
1-
b101 2
1#
#2310
0#
#2315
b1100011 1
1.
0-
b101 2
1#
#2320
0#
#2325
b1100010 1
1.
b101 2
1#
#2330
0#
#2335
b1100001 1
1.
b101 2
1#
#2340
0#
#2345
b1100000 1
1.
b101 2
1#
#2350
0#
#2355
b1011111 1
1.
b101 2
1#
#2360
0#
#2365
b1011110 1
1.
b101 2
1#
#2370
0#
#2375
b1011101 1
1.
b101 2
1#
#2380
0#
#2385
b1011100 1
1.
b101 2
1#
#2390
0#
#2395
b1011011 1
1.
b101 2
1#
#2400
0#
#2405
b1011010 1
1.
b101 2
1#
#2410
0#
#2415
b1011001 1
1.
b101 2
1#
#2420
0#
#2425
b1011000 1
1.
b101 2
1#
#2430
0#
#2435
b1010111 1
1.
b101 2
1#
#2440
0#
#2445
b1010110 1
1.
b101 2
1#
#2450
0#
#2455
b1010101 1
1.
b101 2
1#
#2460
0#
#2465
b1010100 1
1.
b101 2
1#
#2470
0#
#2475
b1010011 1
1.
b101 2
1#
#2480
0#
#2485
b1010010 1
1.
b101 2
1#
#2490
0#
#2495
b1010001 1
1.
b101 2
1#
#2500
0#
#2505
b1010000 1
1.
b101 2
1#
#2510
0#
#2515
b1001111 1
1.
b101 2
1#
#2520
0#
#2525
b1001110 1
1.
b101 2
1#
#2530
0#
#2535
b1001101 1
1.
b101 2
1#
#2540
0#
#2545
b1001100 1
1.
b101 2
1#
#2550
0#
#2555
b1001011 1
1.
b101 2
1#
#2560
0#
#2565
b1001010 1
1.
b101 2
1#
#2570
0#
#2575
b1001001 1
1.
b101 2
1#
#2580
0#
#2585
b1001000 1
1.
b101 2
1#
#2590
0#
#2595
b1000111 1
1.
b101 2
1#
#2600
0#
#2605
b1000110 1
1.
b101 2
1#
#2610
0#
#2615
b1000101 1
1.
b101 2
1#
#2620
0#
#2625
b1000100 1
1.
b101 2
1#
#2630
0#
#2635
b1000011 1
1.
b101 2
1#
#2640
0#
#2645
b1000010 1
1.
b101 2
1#
#2650
0#
#2655
b1000001 1
1.
b101 2
1#
#2660
0#
#2665
b1000000 1
1.
b101 2
1#
#2670
0#
#2675
b111111 1
1.
b101 2
1#
#2680
0#
#2685
b111110 1
1.
b101 2
1#
#2690
0#
#2695
b111101 1
1.
b101 2
1#
#2700
0#
#2705
b111100 1
1.
b101 2
1#
#2710
0#
#2715
b111011 1
1.
b101 2
1#
#2720
0#
#2725
b111010 1
1.
b101 2
1#
#2730
0#
#2735
b111001 1
1.
b101 2
1#
#2740
0#
#2745
b111000 1
1.
b101 2
1#
#2750
0#
#2755
b110111 1
1.
b101 2
1#
#2760
0#
#2765
b110110 1
1.
b101 2
1#
#2770
0#
#2775
b110101 1
1.
b101 2
1#
#2780
0#
#2785
b110100 1
1.
b101 2
1#
#2790
0#
#2795
b110011 1
1.
b101 2
1#
#2800
0#
#2805
b110010 1
1.
b101 2
1#
#2810
0#
#2815
b110001 1
1.
b101 2
1#
#2820
0#
#2825
b110000 1
1.
b101 2
1#
#2830
0#
#2835
b101111 1
1.
b101 2
1#
#2840
0#
#2845
b101110 1
1.
b101 2
1#
#2850
0#
#2855
b101101 1
1.
b101 2
1#
#2860
0#
#2865
b101100 1
1.
b101 2
1#
#2870
0#
#2875
b101011 1
1.
b101 2
1#
#2880
0#
#2885
b101010 1
1.
b101 2
1#
#2890
0#
#2895
b101001 1
1.
b101 2
1#
#2900
0#
#2905
b101000 1
1.
b101 2
1#
#2910
0#
#2915
b100111 1
1.
b101 2
1#
#2920
0#
#2925
b100110 1
1.
b101 2
1#
#2930
0#
#2935
b100101 1
1.
b101 2
1#
#2940
0#
#2945
b100100 1
1.
b101 2
1#
#2950
0#
#2955
b100011 1
1.
b101 2
1#
#2960
0#
#2965
b100010 1
1.
b101 2
1#
#2970
0#
#2975
b100001 1
1.
b101 2
1#
#2980
0#
#2985
b100000 1
1.
b101 2
1#
#2990
0#
#2995
b11111 1
1.
b101 2
1#
#3000
0#
#3005
b11110 1
1.
b101 2
1#
#3010
0#
#3015
b11101 1
1.
b101 2
1#
#3020
0#
#3025
b11100 1
1.
b101 2
1#
#3030
0#
#3035
b11011 1
1.
b101 2
1#
#3040
0#
#3045
b11010 1
1.
b101 2
1#
#3050
0#
#3055
b11001 1
1.
b101 2
1#
#3060
0#
#3065
b11000 1
1.
b101 2
1#
#3070
0#
#3075
b10111 1
1.
b101 2
1#
#3080
0#
#3085
b10110 1
1.
b101 2
1#
#3090
0#
#3095
b10101 1
1.
b101 2
1#
#3100
0#
#3105
b10100 1
1.
b101 2
1#
#3110
0#
#3115
b10011 1
1.
b101 2
1#
#3120
0#
#3125
b10010 1
1.
b101 2
1#
#3130
0#
#3135
b10001 1
1.
b101 2
1#
#3140
0#
#3145
b10000 1
1.
b101 2
1#
#3150
0#
#3155
b1111 1
1.
b101 2
1#
#3160
0#
#3165
b1110 1
1.
b101 2
1#
#3170
0#
#3175
b1101 1
1.
b101 2
1#
#3180
0#
#3185
b1100 1
1.
b101 2
1#
#3190
0#
#3195
b1011 1
1.
b101 2
1#
#3200
0#
#3205
b1010 1
1.
b101 2
1#
#3210
0#
#3215
b1001 1
1.
b101 2
1#
#3220
0#
#3225
b1000 1
1.
b101 2
1#
#3230
0#
#3235
b111 1
1.
b101 2
1#
#3240
0#
#3245
b110 1
1.
b101 2
1#
#3250
0#
#3255
b101 1
1.
b101 2
1#
#3260
0#
#3265
b100 1
1.
b101 2
1#
#3270
0#
#3275
b11 1
1.
b101 2
1#
#3280
0#
#3285
b10 1
1.
b101 2
1#
#3290
0#
#3295
b1 1
1.
b101 2
1#
#3300
0#
#3305
b0 1
1.
b101 2
1#
#3310
0#
#3315
1!
0"
1.
b101 2
1#
#3320
0#
#3325
1.
b101 2
1#
#3330
0#
#3335
1.
b101 2
1#
#3340
0#
#3345
1.
b101 2
1#
#3350
0#
b0 %
b0 *
#3355
1.
b101 2
1#
#3360
0#
#3365
1.
b101 2
1#
#3370
0#
#3375
1.
b101 2
1#
#3380
0#
#3385
1.
b101 2
1#
#3390
0#
#3395
1.
b101 2
1#
#3400
0#
b0 '
b0 ,
#3405
1.
b101 2
1#
#3410
0#
#3415
1.
b101 2
1#
#3420
0#
#3425
1.
b101 2
1#
#3430
0#
#3435
1.
b101 2
1#
#3440
0#
#3445
1.
b101 2
1#
#3450
0#
#3455
1.
b101 2
1#
#3460
0#
#3465
1.
b101 2
1#
#3470
0#
#3475
1.
b101 2
1#
#3480
0#
#3485
1.
b101 2
1#
#3490
0#
#3495
1.
b101 2
1#
#3500
0#
b1000 %
b1000 *
#3505
1.
b101 2
1#
#3510
0#
#3515
1.
b101 2
1#
#3520
0#
#3525
1.
b101 2
1#
#3530
0#
#3535
1.
b101 2
1#
#3540
0#
#3545
1.
b101 2
1#
#3550
0#
b1000 '
b1000 ,
#3555
b11 /
1.
b101 2
1#
#3560
0#
#3565
1.
b101 2
1#
#3570
0#
#3575
1.
b101 2
1#
#3580
0#
#3585
1.
b101 2
1#
#3590
0#
#3595
1.
b101 2
1#
#3600
0#
b0 %
b0 *
#3605
1.
b101 2
1#
#3610
0#
#3615
1.
b101 2
1#
#3620
0#
#3625
1.
b101 2
1#
#3630
0#
#3635
1.
b101 2
1#
#3640
0#
#3645
1.
b101 2
1#
#3650
0#
b0 '
b0 ,
#3655
1.
b101 2
1#
#3660
0#
#3665
1.
b101 2
1#
#3670
0#
#3675
1.
b101 2
1#
#3680
0#
#3685
1.
b101 2
1#
#3690
0#
#3695
1.
b101 2
1#
#3700
0#
b10 $
b10 )
#3705
1.
b11 0
b101 2
1#
#3710
0#
#3715
1.
b101 2
1#
#3720
0#
#3725
1.
b101 2
1#
#3730
0#
b0 $
b0 )
#3735
1.
b101 2
1#
#3740
0#
#3745
1.
b101 2
1#
#3750
0#
b100 %
b100 *
#3755
1.
b101 2
1#
#3760
0#
#3765
1.
b101 2
1#
#3770
0#
#3775
1.
b101 2
1#
#3780
0#
#3785
1.
b101 2
1#
#3790
0#
#3795
1.
b101 2
1#
#3800
0#
b100 '
b100 ,
#3805
b10 /
1.
b101 2
1#
#3810
0#
#3815
1.
b101 2
1#
#3820
0#
#3825
1.
b101 2
1#
#3830
0#
#3835
1.
b101 2
1#
#3840
0#
#3845
1.
b101 2
1#
#3850
0#
b0 %
b0 *
#3855
1.
b101 2
1#
#3860
0#
#3865
1.
b101 2
1#
#3870
0#
#3875
1.
b101 2
1#
#3880
0#
#3885
1.
b101 2
1#
#3890
0#
#3895
1.
b101 2
1#
#3900
0#
b0 '
b0 ,
#3905
1.
b101 2
1#
#3910
0#
#3915
1.
b101 2
1#
#3920
0#
#3925
1.
b101 2
1#
#3930
0#
#3935
1.
b101 2
1#
#3940
0#
#3945
1.
b101 2
1#
#3950
0#
#3955
1.
b101 2
1#
#3960
0#
#3965
1.
b101 2
1#
#3970
0#
#3975
1.
b101 2
1#
#3980
0#
#3985
1.
b101 2
1#
#3990
0#
#3995
1.
b101 2
1#
#4000
0#
b10 %
b10 *
#4005
1.
b101 2
1#
#4010
0#
#4015
1.
b101 2
1#
#4020
0#
#4025
1.
b101 2
1#
#4030
0#
#4035
1.
b101 2
1#
#4040
0#
#4045
1.
b101 2
1#
#4050
0#
b10 '
b10 ,
#4055
b1 0
b1100100 1
0!
b1 /
1.
b101 2
1#
#4060
0#
#4065
b1100011 1
1.
b101 2
1#
#4070
0#
#4075
b1100010 1
1.
b101 2
1#
#4080
0#
#4085
b1100001 1
1.
b101 2
1#
#4090
0#
#4095
b1100000 1
1.
b101 2
1#
#4100
0#
#4105
b1011111 1
1.
b101 2
1#
#4110
0#
#4115
b1011110 1
1.
b101 2
1#
#4120
0#
#4125
b1011101 1
1.
b101 2
1#
#4130
0#
#4135
b1011100 1
1.
b101 2
1#
#4140
0#
#4145
b1011011 1
1.
b101 2
1#
#4150
0#
#4155
b1011010 1
1.
b101 2
1#
#4160
0#
#4165
b1011001 1
1.
b101 2
1#
#4170
0#
#4175
b1011000 1
1.
b101 2
1#
#4180
0#
#4185
b1010111 1
1.
b101 2
1#
#4190
0#
#4195
b1010110 1
1.
b101 2
1#
#4200
0#
#4205
b1010101 1
1.
b101 2
1#
#4210
0#
#4215
b1010100 1
1.
b101 2
1#
#4220
0#
#4225
b1010011 1
1.
b101 2
1#
#4230
0#
#4235
b1010010 1
1.
b101 2
1#
#4240
0#
#4245
b1010001 1
1.
b101 2
1#
#4250
0#
#4255
b1010000 1
1.
b101 2
1#
#4260
0#
#4265
b1001111 1
1.
b101 2
1#
#4270
0#
#4275
b1001110 1
1.
b101 2
1#
#4280
0#
#4285
b1001101 1
1.
b101 2
1#
#4290
0#
#4295
b1001100 1
1.
b101 2
1#
#4300
0#
#4305
b1001011 1
1.
b101 2
1#
#4310
0#
#4315
b1001010 1
1.
b101 2
1#
#4320
0#
#4325
b1001001 1
1.
b101 2
1#
#4330
0#
#4335
b1001000 1
1.
b101 2
1#
#4340
0#
#4345
b1000111 1
1.
b101 2
1#
#4350
0#
#4355
b1000110 1
1.
b101 2
1#
#4360
0#
#4365
b1000101 1
1.
b101 2
1#
#4370
0#
#4375
b1000100 1
1.
b101 2
1#
#4380
0#
#4385
b1000011 1
1.
b101 2
1#
#4390
0#
#4395
b1000010 1
1.
b101 2
1#
#4400
0#
#4405
b1000001 1
1.
b101 2
1#
#4410
0#
#4415
b1000000 1
1.
b101 2
1#
#4420
0#
#4425
b111111 1
1.
b101 2
1#
#4430
0#
#4435
b111110 1
1.
b101 2
1#
#4440
0#
#4445
b111101 1
1.
b101 2
1#
#4450
0#
#4455
b111100 1
1.
b101 2
1#
#4460
0#
#4465
b111011 1
1.
b101 2
1#
#4470
0#
#4475
b111010 1
1.
b101 2
1#
#4480
0#
#4485
b111001 1
1.
b101 2
1#
#4490
0#
#4495
b111000 1
1.
b101 2
1#
#4500
0#
#4505
b110111 1
1.
b101 2
1#
#4510
0#
#4515
b110110 1
1.
b101 2
1#
#4520
0#
#4525
b110101 1
1.
b101 2
1#
#4530
0#
#4535
b110100 1
1.
b101 2
1#
#4540
0#
#4545
b110011 1
1.
b101 2
1#
#4550
0#
#4555
b110010 1
1.
b101 2
1#
#4560
0#
#4565
b110001 1
1.
b101 2
1#
#4570
0#
#4575
b110000 1
1.
b101 2
1#
#4580
0#
#4585
b101111 1
1.
b101 2
1#
#4590
0#
#4595
b101110 1
1.
b101 2
1#
#4600
0#
#4605
b101101 1
1.
b101 2
1#
#4610
0#
#4615
b101100 1
1.
b101 2
1#
#4620
0#
#4625
b101011 1
1.
b101 2
1#
#4630
0#
#4635
b101010 1
1.
b101 2
1#
#4640
0#
#4645
b101001 1
1.
b101 2
1#
#4650
0#
#4655
b101000 1
1.
b101 2
1#
#4660
0#
#4665
b100111 1
1.
b101 2
1#
#4670
0#
#4675
b100110 1
1.
b101 2
1#
#4680
0#
#4685
b100101 1
1.
b101 2
1#
#4690
0#
#4695
b100100 1
1.
b101 2
1#
#4700
0#
#4705
b100011 1
1.
b101 2
1#
#4710
0#
#4715
b100010 1
1.
b101 2
1#
#4720
0#
#4725
b100001 1
1.
b101 2
1#
#4730
0#
#4735
b100000 1
1.
b101 2
1#
#4740
0#
#4745
b11111 1
1.
b101 2
1#
#4750
0#
#4755
b11110 1
1.
b101 2
1#
#4760
0#
#4765
b11101 1
1.
b101 2
1#
#4770
0#
#4775
b11100 1
1.
b101 2
1#
#4780
0#
#4785
b11011 1
1.
b101 2
1#
#4790
0#
